{
  "project_info": {
    "project_number": "1091378787756",
    "firebase_url": "https://litelo-42353.firebaseio.com",
    "project_id": "litelo-42353",
    "storage_bucket": "litelo-42353.appspot.com"
  },
  "client": [
    {
      "client_info": {
        "mobilesdk_app_id": "1:1091378787756:android:f4df10fbc44b592c93b609",
        "android_client_info": {
          "package_name": "com.example.litelo"
        }
      },
      "oauth_client": [
        {
          "client_id": "1091378787756-7m4rpooltg3kqr0i4qkj0s2so9hrq173.apps.googleusercontent.com",
          "client_type": 1,
          "android_info": {
            "package_name": "com.example.litelo",
            "certificate_hash": "aef2ac410474a1f4a9f0fd40aa4d49b1c4d9b08d"
          }
        },
        {
          "client_id": "1091378787756-4ip1d9t7089jnfcoeg3l56108d2vluud.apps.googleusercontent.com",
          "client_type": 1,
          "android_info": {
            "package_name": "com.example.litelo",
            "certificate_hash": "203746e24f91cb262427479d881ddd58b745235d"
          }
        },
        {
          "client_id": "1091378787756-cva940ll9v86oge4au4g0u9dku95a895.apps.googleusercontent.com",
          "client_type": 1,
          "android_info": {
            "package_name": "com.example.litelo",
            "certificate_hash": "d0f0784af68d580e07a7f64b1aff0fb9b79dcda6"
          }
        },
        {
          "client_id": "1091378787756-7ui03f7cdrm57ggede3pqc004g4a690a.apps.googleusercontent.com",
          "client_type": 3
        }
      ],
      "api_key": [
        {
          "current_key": "AIzaSyCLAwSgPEaWv2Sb-imLg2ogd4HmWTm58gk"
        }
      ],
      "services": {
        "appinvite_service": {
          "other_platform_oauth_client": [
            {
              "client_id": "1091378787756-7ui03f7cdrm57ggede3pqc004g4a690a.apps.googleusercontent.com",
              "client_type": 3
            }
          ]
        }
      }
    }
  ],
  "configuration_version": "1"
}